README.md
setup.py
samplexrsasas/__init__.py
samplexrsasas/samplexrs.py
samplexrsasas.egg-info/PKG-INFO
samplexrsasas.egg-info/SOURCES.txt
samplexrsasas.egg-info/dependency_links.txt
samplexrsasas.egg-info/requires.txt
samplexrsasas.egg-info/top_level.txt